etlcli/__init__.py
etlcli/cli.py
etlcli/extractor.py
etlcli/loader.py
etlcli/transformer.py
etlcli/utils.py
etlcli-0.5.16.dist-info/LICENSE
etlcli-0.5.16.dist-info/METADATA
etlcli-0.5.16.dist-info/WHEEL
etlcli-0.5.16.dist-info/entry_points.txt
etlcli-0.5.16.dist-info/top_level.txt
etlcli-0.5.16.dist-info/RECORD
