Metadata-Version: 2.1
Name: etlcli
Version: 0.5.16
Summary: A small python package for simple etl processing
Home-page: https://godatadriven.com/blog/a-practical-guide-to-setuptools-and-pyproject-toml
Author: Piotr Szmelczynski
Author-email: piotr.szmelczynski@gmail.com
License: MIT
Classifier: License :: OSI Approved :: BSD License
Classifier: Programming Language :: Python :: 3.6
Classifier: Programming Language :: Python :: 3.7
Classifier: Programming Language :: Python :: 3.8
Classifier: Programming Language :: Python :: 3.9
Requires-Python: >=3.6
License-File: LICENSE
